{
  "name": "Olive Hart",
  "age": 27,
  "address": {
    "street": "Sutim Lane",
    "city": "Zajhueke",
    "state": "IA",
    "zip": "95624"
  },
  "contact": {
    "phone": "(965) 596-4777",
    "servicePhone": "800416165"
  },
  "birthday": "1998-04-01T03:57:56.857Z",
  "ip": "241.161.5.141",
  "foo": "bar",
  "profile": {
    "about": "Vawlel ve cuur kow mok bejogko kupocu tiez hika rabuj asoom mozis joneje linet hitok ehcujvuf wutrot. Vowgawcem vud wi zu basem ovusasar evituwi fuheoc guh kodriev og bocgelpu la wacdoozu uwaur ceje bofiz. Uw tawugu tirje tuc ramil dew ekaen ge wulca ribgeb fudgir ku ilhegi pigeja fifemej jolezani cangocuc su. Pi dit naci zoh peflig cek juami devceetu razho ji nuki vobdih tihwiwej boas ra mugupzi rinzec. Zulu belpu bipbuvum relnar bik tugha igo juzenego co vewpi cezvof nahjasi fipovzed hazpi otaseopo saile ru roki.",
    "bio": "Jud iwien moteguj zecreme hoca oke mosuwuj vic kouzdom oce tuhovtad po bal. Fupok isellor cutlo mantiffuw pes ki ifcuw hoogmic ekahu jer funudano todfa pen. Pos bavafpu urnip nimod dow jibhuru in ajbiz jurfapwih fembuzce otu nedremtid olcovoc vasegul uma kobuhisen ta. Cojalar koslukjog ace zeagzip itla mucneis to upo nepof onalinto weste bih askur le hifjuta homejkot bennu. Ko josa oheden kubsa pe zamramit udi vicetu unfo hutda lezitop ezis re wen fopufnu imbolpor sa erufaf."
  },
  "apiKey": "3c410237fed83521078db1abffe3f556b4aaf0d4fe0d20c9882cb1c9e2f3f49f",
  "currency": {
    "code": "CUC",
    "name": "Cuba Convertible Peso"
  }
}