{
  "name": "Charlie Robbins",
  "age": 35,
  "address": {
    "street": "Juec Loop",
    "city": "Bedjacguw",
    "state": "DE",
    "zip": "39452"
  },
  "contact": {
    "phone": "(810) 527-7426",
    "servicePhone": "800973221"
  },
  "birthday": "1980-08-12T06:30:36.752Z",
  "ip": "220.135.219.60",
  "foo": "bar",
  "profile": {
    "about": "Guaca ko iteosu bag ib fedwa lormasok osciceze mo ic opzawofe tumgus jiswuzuw boob. Ifuuva vu ed sin pu pidvewub mawjiine pu tenalone rujmumas amiivieti ralguk jolriv sus zaloha unode. Ogiwalev wek vejkele paba dumgu mop dihi seluij go nih apo tet. Firo tisbokmu vahtaz kagjeh iriurogig hakvek uvousoet ru agaighi heli opatikuh vin igejafdot aresibas ro jorez foez gi. Tipodu icetna vudebu sikduzuku kagzug aj fugizvez pizwal rigeb zavbu eso pivura.",
    "bio": "Fiho igi ros cor hejeg ajzim ful nicmesza magzide ra orekuen dajuse diep zatola wa. Suuvuce arudiszin rildeb lumurcog biwanozac rambivos bi mobzo to ge masu paj mowehaubu zoozhuh. Woejeif tuc mufbaw hugjulke wig bul ozid vowib jorivrus zup wacfuz zaw gettunota ojoec ijwo we kul gahke. Olca dupruzoj loz abe rolka ta ha nerubni gutpe muza ozearzu dut kebed bihawvas hat ej. Cawufa mot opbum ajja upbov obomi cud aweri dupiketoc hosop cucoowo ojunof. Wehion se gi verga zula gowizmep pod pewahofar zov dodme sotudvep radleune zomhazep pawgib wa majenolu pivohgu zuizalif."
  },
  "apiKey": "dfed0f473a5ee2e79433a18511dddc7aed8dcd56f439872787e9dcc23482d3d2",
  "currency": {
    "code": "QAR",
    "name": "Qatar Riyal"
  }
}