{
  "name": "Kyle Huff",
  "age": 27,
  "address": {
    "street": "Biguco Manor",
    "city": "Nigpose",
    "state": "MN",
    "zip": "18692"
  },
  "contact": {
    "phone": "(850) 278-6984",
    "servicePhone": "800976357"
  },
  "birthday": "1973-09-09T14:58:58.600Z",
  "ip": "87.76.56.215",
  "foo": "bar",
  "profile": {
    "about": "Behazcil jape cafas ifiip puhev ul gujnoco lize menwigtot tepdom vezez wanejce nafani pumuduv makjugub ogutud sijer. Uw uriezo ifapi tuhgutti be mowke sajir viava zal itto lilze bebba racif hal ridohev tihta fuv. Runho va bo wo civat obikoavi pekagdut etocu acuze kup souk afe satug.",
    "bio": "Sumu niri luhukma vofmicbep apakut mu nir paflat usisojha ziti wuaz ga aguzek ejucus fubsivum pohuhu avemah za. Raok oju hu vigur wofri la ler nufratic hudhicisa ep re okibufip sumovog wu gimekug bicas sifewo. Bahlusi duvike iblag motam hadbig jehim gu erup gu humevla motvafsah ranlakac huukilo odusi tomit owo. Ikawurup uba jubguvci ivoarahud le jesos ajiga taaf sun de ivuuviiha hocjew reucezaf itne. Roguzgo fifahjo boh apjente bisjacjam hodev ulbog leanavi mam kenvok ves egha kuv bukip eje gac epcah zefiket."
  },
  "apiKey": "fad8e6daf9dc127a12cf0573d628484c4b00e5e727b360637ee4392947558e04",
  "currency": {
    "code": "AED",
    "name": "United Arab Emirates Dirham"
  }
}