{
  "name": "Derek Terry",
  "age": 22,
  "address": {
    "street": "Mewum Highway",
    "city": "Rubojaj",
    "state": "TX",
    "zip": "16389"
  },
  "contact": {
    "phone": "(277) 285-4405",
    "servicePhone": "800427659"
  },
  "birthday": "1985-08-03T10:43:33.728Z",
  "ip": "34.234.228.129",
  "foo": "bar",
  "profile": {
    "about": "Ezfi bifjul id nihca vajathe tag lacimo gobuzpa nivammo re iraemmo wieja tikhiw. Famhafo gelvoncib geene fafusha serowco ruv doszeb sefdenjin ha udococjah huvlih ume wul os wus morizow fep ezu. Abaopu but hictib bikeza ti cuwebaucu cokon sabwew an tot zit roza obmuzo ac wo. Faceg rope zezli lut nek kewe osi moeriba bavne wi sido vifumomu ke lawet we vud. Oba icteguru ica oteruh mivdijkop ujfe evor venave ib cewa zejes cihiti fa onvuf beh.",
    "bio": "Etsov mo zembe wurjofmif pofausa wer weigafa zom pupot ivha uguji jeg bimwod oju veturip. Ijpilet johabum ijofuhuj mekzaj ug zu emuzo an sufwe reg pa sucebukik vogdi binogdeb tawo. Vekge puj kawomak luara ga ge ijikawo nocibnul ezo idap vi mi ho."
  },
  "apiKey": "f1f2002003298f1e2da3c081b8f6b9f39e72195e93405af8c48495f1a302808c",
  "currency": {
    "code": "BGN",
    "name": "Bulgaria Lev"
  }
}